{
 "actions": [],
 "creation": "2026-06-26 12:00:00.000000",
 "doctype": "DocType",
 "editable_grid": 1,
 "engine": "InnoDB",
 "field_order": ["line_type", "item", "horse", "groom_profile", "tournament", "reference_doctype", "reference_name", "description", "quantity", "unit", "rate", "tax_amount", "total", "cost_category", "affects_inventory"],
 "fields": [
  {"default": "Item", "fieldname": "line_type", "fieldtype": "Select", "in_list_view": 1, "label": "Detail Type", "options": "Item\nHorse\nGroom\nTournament\nService\nOther"},
  {"depends_on": "eval:doc.line_type==='Item'", "fieldname": "item", "fieldtype": "Link", "in_list_view": 1, "label": "Item", "options": "Item"},
  {"depends_on": "eval:doc.line_type==='Horse'", "fieldname": "horse", "fieldtype": "Link", "label": "Horse", "options": "Horse"},
  {"depends_on": "eval:doc.line_type==='Groom'", "fieldname": "groom_profile", "fieldtype": "Link", "label": "Groom", "options": "Groom Profile"},
  {"depends_on": "eval:doc.line_type==='Tournament'", "fieldname": "tournament", "fieldtype": "Data", "label": "Tournament / Event"},
  {"fieldname": "reference_doctype", "fieldtype": "Link", "label": "Reference Type", "options": "DocType"},
  {"depends_on": "eval:doc.reference_doctype", "fieldname": "reference_name", "fieldtype": "Dynamic Link", "label": "Reference", "options": "reference_doctype"},
  {"fieldname": "description", "fieldtype": "Small Text", "in_list_view": 1, "label": "Description"},
  {"default": "1", "fieldname": "quantity", "fieldtype": "Float", "in_list_view": 1, "label": "Quantity"},
  {"fieldname": "unit", "fieldtype": "Select", "label": "Unit", "options": "\nkg\ng\nlb\nscoop\nflake\nbag\nml\nl\nunit\nset\npair"},
  {"default": "0", "fieldname": "rate", "fieldtype": "Currency", "in_list_view": 1, "label": "Rate"},
  {"default": "0", "fieldname": "tax_amount", "fieldtype": "Currency", "label": "Tax Amount"},
  {"fieldname": "total", "fieldtype": "Currency", "in_list_view": 1, "label": "Total", "read_only": 1},
  {"default": "Other", "fieldname": "cost_category", "fieldtype": "Select", "in_list_view": 1, "label": "Cost Category", "options": "Feed\nEquipment\nSupplies\nSupplements\nGroom Salary\nOvertime Pay\nBenefits\nHorse Purchase\nHorse Sale\nMedical\nFarrier\nTraining\nTournament\nTransport\nService\nOther"},
  {"default": "1", "depends_on": "eval:doc.line_type==='Item'", "fieldname": "affects_inventory", "fieldtype": "Check", "label": "Affects Inventory"}
 ],
 "grid_page_length": 50,
 "istable": 1,
 "links": [],
 "modified": "2026-06-26 12:00:00.000000",
 "modified_by": "Administrator",
 "module": "Polomanagement",
 "name": "Vendor Quote Line",
 "owner": "Administrator",
 "permissions": [],
 "row_format": "Dynamic",
 "sort_field": "idx",
 "sort_order": "ASC",
 "states": []
}
